stickerify/__init__.py
stickerify/screenshot.py
stickerify/stickerify.py
stickerify/utils.py
stickerify-1.0.1.dist-info/LICENSE
stickerify-1.0.1.dist-info/METADATA
stickerify-1.0.1.dist-info/WHEEL
stickerify-1.0.1.dist-info/entry_points.txt
stickerify-1.0.1.dist-info/top_level.txt
stickerify-1.0.1.dist-info/RECORD
