Metadata-Version: 2.1
Name: stickerify
Version: 1.0.1
Summary: Telegram stickers from screenshots
Home-page: https://github.com/Akiiino/Stickerify.git
Author: Akiiino
Author-email: akiiino@akiiino.me
License: UNKNOWN
Platform: UNKNOWN
Classifier: Programming Language :: Python :: 3
Classifier: License :: OSI Approved :: MIT License
Classifier: Operating System :: OS Independent
Requires-Python: >=3.5
Requires-Dist: numpy (>=1.11.1)
Requires-Dist: matplotlib (<3.1,>=1.5.1)
Requires-Dist: pillow (>=6.0.0)
Requires-Dist: scipy (>=1.0.0)
Requires-Dist: scikit-image (>=0.10.0)
